{
  "generatedAt": "2026-04-13T11:01:42.641Z",
  "weekday": 1,
  "menus": [
    {
      "id": "andel-restaurant",
      "name": "Anděl Restaurant",
      "url": "https://www.restauraceandel.cz/denni-nabidka",
      "source": "live",
      "status": "ok",
      "message": "Načteno.",
      "items": [
        {
          "type": "soup",
          "name": "Krém z medvědího česneku s krutóny",
          "price": 49
        },
        {
          "type": "main",
          "name": "Vepřová roláda, bramborová kaše, rajčatový salátek",
          "price": 174
        },
        {
          "type": "main",
          "name": "Spatzle, olivy, sýrová omáčka, baby špenát",
          "price": 184
        },
        {
          "type": "main",
          "name": "Burrito, kuřecí maso, zeleninou, ledový salát, zakysaná smetana, guacamole",
          "price": 184
        },
        {
          "type": "main",
          "name": "Čtvrtka pečené kachny, zelí, bramborové knedlíky",
          "price": 238
        }
      ]
    },
    {
      "id": "bife-restaurant",
      "name": "Bife Restaurant",
      "url": "https://biferestaurant.cz/pages/denni-menu",
      "source": "live",
      "status": "ok",
      "message": "Načteno.",
      "items": [
        {
          "type": "soup",
          "name": "Hovězí vývar s masem, zeleninou a nudlemi",
          "price": 38
        },
        {
          "type": "main",
          "name": "Frankfurtská hovězí pečeně, houskové knedlíky/ rýže",
          "price": 175
        },
        {
          "type": "main",
          "name": "Smažený holandský řízek, bramborová kaše, okurka",
          "price": 169
        },
        {
          "type": "main",
          "name": "Krůtí nudličky s hlívou, cizrnou a špenátem, dušená rýže )",
          "price": 175
        },
        {
          "type": "main",
          "name": "Fusilli s rajčaty, ančovičkami, olivami, kapary, česnekem, hladkolistou petrželí a parmazánem",
          "price": 175
        }
      ]
    },
    {
      "id": "corleone-andel",
      "name": "Corleone Anděl",
      "url": "https://www.corleone.cz/poledni-menu-andel",
      "source": "live",
      "status": "ok",
      "message": "Načteno.",
      "items": [
        {
          "type": "soup",
          "name": "KRÉM Z PEČENÉ MRKVE S CHILLI, ZÁZVOREM, KOKOSOVÝM MLÉKEM A SEMÍNKY",
          "price": 69
        },
        {
          "type": "main",
          "name": "SPAGHETTI S ITALSKOU SLANINOU, CHERRY RAJČATY, ČESNEKEM, BAZALKOU, RUKOLOU A PARMEZÁNEM, ZJEMNĚNÉ MÁSLEM",
          "price": 185
        },
        {
          "type": "main",
          "name": "PEČENÝ LILEK S RAJČATY A BAZALKOU, GRATINOVANÝ KOZÍM SÝREM A MOZZARELLOU, LISTOVÝ SALÁTEK",
          "price": 185
        },
        {
          "type": "main",
          "name": "GRILOVANÝ KUŘECÍ STEAK Z VYKOSTĚNÉHO STEHNA S TEPLOU SMETANOVOU SALSOU SE SLANINOU, CIBULKOU, JALAPENOS A OREGÁNEM, ŠŤOUCHANÉ BRAMBORY S JARNÍ CIBULKOU",
          "price": 210
        },
        {
          "type": "main",
          "name": "PIZZA NA SMETANOVÉM ZÁKLADĚ S MOZZARELLOU, KARI, KRŮTÍM MASEM A JARNÍ CIBULKOU",
          "price": 185
        }
      ]
    },
    {
      "id": "smichovna",
      "name": "Smíchovna",
      "url": "https://www.smichovna.cz/tydenni-nabidka",
      "source": "live",
      "status": "ok",
      "message": "Načteno.",
      "items": [
        {
          "type": "soup",
          "name": "Žampionový krém se smetanou a krutony",
          "price": 45
        },
        {
          "type": "main",
          "name": "Salát s kuřecím prsem na grilu, rukolou, listovým salátem, červenou řepou, rajčetem, sýrem niva a dresinkem z citronové šťávy, medu a hrubozrnné hořčice, opečený toast",
          "price": 189
        },
        {
          "type": "main",
          "name": "Křenová omáčka s hovězí pečení a houskovým knedlíkem",
          "price": 199
        },
        {
          "type": "main",
          "name": "Medailonky z telecí svíčkové na grilu s fazolkami na slanině, šťouchaným bramborem a silnou šťávou",
          "price": 209
        },
        {
          "type": "main",
          "name": "Vegetariánský burger s kozím sýrem – listový salát, rajče, grilovaný kozí sýr, karamelizovaná cibulka a česneková majonéza, hranolky",
          "price": 249
        },
        {
          "type": "main",
          "name": "Domácí lívance s omáčkou z lesních plodů a zakysanou smetanou",
          "price": 149
        }
      ]
    },
    {
      "id": "smichovska-formanka",
      "name": "Smíchovská Formanka",
      "url": "http://smichovskaformanka.cz/",
      "source": "live",
      "status": "ok",
      "message": "Načteno.",
      "items": [
        {
          "type": "soup",
          "name": "- žampionový krém s krutony",
          "price": 45
        },
        {
          "type": "main",
          "name": "Špagety s rajčatovou omáčkou, masové kuličky",
          "price": 175
        },
        {
          "type": "main",
          "name": "Smažený hermelín, vařený brambor, tatarka",
          "price": 179
        },
        {
          "type": "main",
          "name": "Dančí guláš s houskovým knedlíkem",
          "price": 185
        },
        {
          "type": "main",
          "name": "Uzená krkovice, spätzle, kysané zelí, smažená cibulka",
          "price": 179
        },
        {
          "type": "main",
          "name": "Grilovaný losos, citronová omáčka, čočka beluga, zelenina",
          "price": 219
        }
      ]
    },
    {
      "id": "u-mamlasu",
      "name": "U Mámy Lásu",
      "url": "https://www.umamlasu.cz/denni-menu-praha",
      "status": "ok",
      "source": "fallback",
      "message": "Zobrazeno ukázkové menu (Nepodařilo se rozpoznat položky menu.).",
      "items": [
        {
          "type": "soup",
          "name": "Česnečka se sýrem",
          "price": 49
        },
        {
          "type": "main",
          "name": "Vídeňský řízek z vepřové kýty, bramborová kaše",
          "price": 189
        },
        {
          "type": "main",
          "name": "Penne arrabbiata",
          "price": 169
        }
      ]
    }
  ]
}
