{
  "generatedAt": "2026-03-20T08:31:57.153Z",
  "weekday": 5,
  "menus": [
    {
      "id": "andel-restaurant",
      "name": "Anděl Restaurant",
      "url": "https://www.restauraceandel.cz/denni-nabidka",
      "source": "live",
      "status": "ok",
      "message": "Načteno.",
      "items": [
        {
          "type": "soup",
          "name": "Brokolicová polévka s krutóny",
          "price": 49
        },
        {
          "type": "main",
          "name": "Smažený holandský řízek, bramborová kaše, okurkový salátek",
          "price": 174
        },
        {
          "type": "main",
          "name": "Těstoviny, mušle, drcená rajčata, cuketa, česnek, bazalka",
          "price": 184
        },
        {
          "type": "main",
          "name": "Plněná zapečená cuketa, sušená rajčata, čedar, ledový salát, tzatziki",
          "price": 184
        },
        {
          "type": "main",
          "name": "Kuřecí plátek se šunkou a broskví, krokety, zeleninová obloha, tatarská omáčka",
          "price": 218
        }
      ]
    },
    {
      "id": "bife-restaurant",
      "name": "Bife Restaurant",
      "url": "https://biferestaurant.cz/pages/denni-menu",
      "source": "live",
      "status": "ok",
      "message": "Načteno (stránka neobsahuje označení dnešního dne, zobrazeny rozpoznané položky).",
      "items": [
        {
          "type": "soup",
          "name": "Bramborový krém s pórkem a uzeninou",
          "price": 38
        },
        {
          "type": "main",
          "name": "Kančí výpečky, červené zelí, bramborové knedlíky",
          "price": 175
        },
        {
          "type": "main",
          "name": "Grilované kuřecí prso, sýrová omáčka, bramborové krokety",
          "price": 175
        },
        {
          "type": "main",
          "name": "Uzená vepřová plec, čočka na kyselo, sázené vejce, okurka",
          "price": 169
        },
        {
          "type": "main",
          "name": "Grilované krevety, arašídová omáčka, jasmínová rýže, řasy wakame",
          "price": 195
        }
      ]
    },
    {
      "id": "corleone-andel",
      "name": "Corleone Anděl",
      "url": "https://www.corleone.cz/poledni-menu-andel",
      "source": "live",
      "status": "ok",
      "message": "Načteno.",
      "items": [
        {
          "type": "main",
          "name": "STAROČESKÁ BRAMBORAČKA S HOUBAMI",
          "price": 69
        },
        {
          "type": "main",
          "name": "CAPELLINI AGLIO OLIO S KREVETAMI, CHILLI PAPRIČAKMI, PETRŽELKOU A PARMEZÁNEM",
          "price": 185
        },
        {
          "type": "main",
          "name": "GRILOVANÝ ŽAMPION PORTOBELLO PLNĚNÝ BOLOŇSKÝM RAGÚ S RAJČATY, ZAPEČENÝ MOZZARELLOU A CHEDDAREM, MALÝ LISTOVÝ SALÁTEK",
          "price": 195
        },
        {
          "type": "main",
          "name": "GRILOVANÁ VEPŘOVÁ PANENKA PLNĚNÁ SUŠENÝMI RAJČATY A ČERSTVOU BAZALKOU S GRATINOVANÝMI BRAMBORAMI A DEMI GLACE",
          "price": 210
        },
        {
          "type": "main",
          "name": "PIZZA NA SMETANOVÉM ZÁKLADĚ S PESTEM ZE SUŠENÝCH RAJČAT, MOZZARELLOU, MORTADELLOU, CAMEMBERTEM A RUKOLOU",
          "price": 185
        }
      ]
    },
    {
      "id": "smichovna",
      "name": "Smíchovna",
      "url": "https://www.smichovna.cz/tydenni-nabidka",
      "source": "live",
      "status": "ok",
      "message": "Načteno.",
      "items": [
        {
          "type": "soup",
          "name": "Delikátní rukolový krém se smetanou a krutony",
          "price": 45
        },
        {
          "type": "main",
          "name": "Maďarský vepřový guláš s klobásou a bramborovými haluškami",
          "price": 189
        },
        {
          "type": "main",
          "name": "Ražniči z kuřecích prsíček s bramborovými kroketami a česnekovým dipem",
          "price": 189
        },
        {
          "type": "main",
          "name": "Salát s vepřovou panenkou, mixem listových salátů, rajčetem, salátovou okurkou, pečenými brambůrkami, zelenými fazolkami a dresinkem z majonézy, pomerančové a citronové šťávy",
          "price": 189
        },
        {
          "type": "main",
          "name": "Hovězí Texas burger – listový salát, rajče, cibulové kroužky, tekutý čedar a dijonská majonéza, hranolky",
          "price": 249
        },
        {
          "type": "main",
          "name": "Domící lívance s omáčkou z lesních plodů a zakysanou smetanou",
          "price": 149
        }
      ]
    },
    {
      "id": "smichovska-formanka",
      "name": "Smíchovská Formanka",
      "url": "http://smichovskaformanka.cz/",
      "source": "live",
      "status": "ok",
      "message": "Načteno.",
      "items": [
        {
          "type": "main",
          "name": "minestrone",
          "price": 45
        },
        {
          "type": "main",
          "name": "Smažený kuřecí řízek, domácí bramborový salát, citrón",
          "price": 179
        },
        {
          "type": "main",
          "name": "Grilovaný sýr halloumi se zeleninovým sal., jogurt. dressing",
          "price": 179
        },
        {
          "type": "main",
          "name": "Pečená selečí pečeně, medové červené zelí, bramborové šišky",
          "price": 185
        },
        {
          "type": "main",
          "name": "Baby špenát",
          "price": 189
        }
      ]
    },
    {
      "id": "u-mamlasu",
      "name": "U Mámy Lásu",
      "url": "https://www.umamlasu.cz/denni-menu-praha",
      "status": "ok",
      "source": "fallback",
      "message": "Zobrazeno ukázkové menu (Nepodařilo se rozpoznat položky menu.).",
      "items": [
        {
          "type": "soup",
          "name": "Česnečka se sýrem",
          "price": 49
        },
        {
          "type": "main",
          "name": "Vídeňský řízek z vepřové kýty, bramborová kaše",
          "price": 189
        },
        {
          "type": "main",
          "name": "Penne arrabbiata",
          "price": 169
        }
      ]
    }
  ]
}
