{
  "generatedAt": "2026-05-25T09:51:31.282Z",
  "weekday": 1,
  "menus": [
    {
      "id": "andel-restaurant",
      "name": "Anděl Restaurant",
      "url": "https://www.restauraceandel.cz/denni-nabidka",
      "source": "live",
      "status": "ok",
      "message": "Načteno.",
      "items": [
        {
          "type": "soup",
          "name": "Chřestový krém s krutóny",
          "price": 49
        },
        {
          "type": "main",
          "name": "Vepřový plátek na žampiónech, hranolky, vepřová šťáva, tatarská omáčka",
          "price": 174
        },
        {
          "type": "main",
          "name": "Znojemská hovězí pečeně, dušená rýže",
          "price": 184
        },
        {
          "type": "main",
          "name": "Těstovinový salát, cherry rajčata, špenát, mozzarella, bazalkové pesto",
          "price": 184
        },
        {
          "type": "main",
          "name": "Kuřecí supreme na grilu, batátové pyré, císařské lusky, demi glace",
          "price": 218
        }
      ]
    },
    {
      "id": "bife-restaurant",
      "name": "Bife Restaurant",
      "url": "https://biferestaurant.cz/pages/denni-menu",
      "source": "live",
      "status": "ok",
      "message": "Načteno.",
      "items": [
        {
          "type": "soup",
          "name": "Hovězí vývar s masem, zeleninou a nudlemi",
          "price": 38
        },
        {
          "type": "main",
          "name": "Štěpánská hovězí pečeně, houskové knedlíky/ rýže",
          "price": 175
        },
        {
          "type": "main",
          "name": "Grilovaná pljeskavica, vařené brambory, ajvar, nakládaná cibule",
          "price": 175
        },
        {
          "type": "main",
          "name": "Indické Butter Chicken, rýže basmati",
          "price": 175
        },
        {
          "type": "main",
          "name": "Penne aglio olio s parmazánem",
          "price": 169
        }
      ]
    },
    {
      "id": "corleone-andel",
      "name": "Corleone Anděl",
      "url": "https://www.corleone.cz/poledni-menu-andel",
      "source": "live",
      "status": "ok",
      "message": "Načteno.",
      "items": [
        {
          "type": "soup",
          "name": "BRAMBOROVO-HRÁŠKOVÝ KRÉM S KRUTONY",
          "price": 69
        },
        {
          "type": "main",
          "name": "RIGATONI S ITALSKOU SALSICCIOU, JARNÍ CIBULKOU, ČESNEKEM A CHILLI PAPRIČKAMI V TOMATOVÉ OMÁČCE, PARMEZÁN",
          "price": 185
        },
        {
          "type": "main",
          "name": "VELKÝ ŘECKÝ SALÁT S GRILOVANÝMI KUŘECÍMI PRSÍČKY, OLIVAMI, FETA SÝREM A TZATZIKI DRESINKEM",
          "price": 195
        },
        {
          "type": "main",
          "name": "DUŠENÁ VEPŘOVÁ KÝTA NA HOUBÁCH S JASMÍNOVOU RÝŽÍ",
          "price": 210
        },
        {
          "type": "main",
          "name": "PIZZA NA TOMATOVÉM ZÁKLADĚ S MOZZARELLOU, SALÁMEM VENTRICINA, CIBULÍ A ČESNEKEM",
          "price": 185
        }
      ]
    },
    {
      "id": "smichovna",
      "name": "Smíchovna",
      "url": "https://www.smichovna.cz/tydenni-nabidka",
      "source": "live",
      "status": "ok",
      "message": "Načteno.",
      "items": [
        {
          "type": "soup",
          "name": "Chřestový krém s bílým vínem, smetanou a krutony",
          "price": 49
        },
        {
          "type": "main",
          "name": "Smažený hermelín s vařeným bramborem a naší tatarskou omáčkou",
          "price": 179
        },
        {
          "type": "main",
          "name": "Salát s kuřecím masem, červenou řepou, listovým salátem, rukolou, rajčetem, vařeným vejcem, sýrem Niva, ořechy a dresinkem z medu, hrubozrnné hořčice a citronové šťávy, opečený toast",
          "price": 189
        },
        {
          "type": "main",
          "name": "Svíčková na smetaně s hovězí pečení, brusinkami a houskovým knedlíkem",
          "price": 199
        },
        {
          "type": "main",
          "name": "Hovězí Texas burger – listový salát, rajče, cibulové kroužky, tekutý čedar a dijonská majonéza, hranolky",
          "price": 259
        },
        {
          "type": "main",
          "name": "Domácí lívance s omáčkou z lesních plodů a zakysanou smetanou",
          "price": 149
        }
      ]
    },
    {
      "id": "smichovska-formanka",
      "name": "Smíchovská Formanka",
      "url": "http://smichovskaformanka.cz/",
      "status": "ok",
      "source": "fallback",
      "message": "Zobrazeno ukázkové menu (Nepodařilo se rozpoznat položky menu.).",
      "items": [
        {
          "type": "soup",
          "name": "Bramboračka",
          "price": 42
        },
        {
          "type": "main",
          "name": "Segedínský guláš, houskový knedlík",
          "price": 175
        },
        {
          "type": "main",
          "name": "Kuřecí nudličky na kari, rýže",
          "price": 172
        }
      ]
    },
    {
      "id": "u-mamlasu",
      "name": "U Mámy Lásu",
      "url": "https://www.umamlasu.cz/denni-menu-praha",
      "status": "ok",
      "source": "fallback",
      "message": "Zobrazeno ukázkové menu (Nepodařilo se rozpoznat položky menu.).",
      "items": [
        {
          "type": "soup",
          "name": "Česnečka se sýrem",
          "price": 49
        },
        {
          "type": "main",
          "name": "Vídeňský řízek z vepřové kýty, bramborová kaše",
          "price": 189
        },
        {
          "type": "main",
          "name": "Penne arrabbiata",
          "price": 169
        }
      ]
    }
  ]
}
